t2/fsm-cicle.v
module ff ( input data, input c, input r, output q);
reg q;
always @(posedge c or negedge r) 
begin
 if(r==1'b0)
  q <= 1'b0; 
 else 
  q <= data; 
end 
endmodule //End 

// ----   FSM alto nível com Case
module statem(clk, reset,a, s);
input clk, reset,a;
output [2:0] s;
reg [2:0] state;  // 3 bits de estado
parameter zero=3'b000,two=3'b001,three=3'b011,four=3'b100,five=3'b101,six = 3'b110;

assign s = (state == zero)? 3'd0:
           (state == two)? 3'd2:
           (state == three)? 3'd3:
           (state == four) ? 3'd4 : 3'd5;   

always @(posedge clk or negedge reset)
     begin
          if (reset==0)
               state = zero; // arbitrario neste exemplo, nao especificado...
          else
               case (state)
                    zero: state = zero;
                    two: 
                      state = five;
                    three:
                      state = six;
                    four:
                      state = two;
                    five: 
                      if(a == 1) state = three;
                      else state = six;
                    six:
                      state = four;
               endcase
     end
endmodule
// FSM com portas logicas
// programar ainda....
module statePorta(input clk, input res, input a, output [2:0] s);
wire [2:0] e;
wire [2:0] p;

assign s = e;
assign p[2] = e[1] & e[0] & ~a;
assign p[1] = (~e[2] & ~e[1] & ~a) | (e[1] & ~e[0] & ~a) | (e[2] & ~a);
assign p[0] = (e[2] & e[0] | e[1] & ~e[0]) | (e[2] & a);

ff  e0(p[0],clk,res,e[0]);
ff  e1(p[1],clk,res,e[1]);
ff  e2(p[2],clk,res,e[2]);

endmodule 

module stateMem(input clk,input res, input a, output [2:0] s);
reg [5:0] StateMachine [0:15]; // 16 linhas de memória, com 6 bits de largura

initial
begin  // Codificar as linhas da memória
StateMachine[0] = 6'd0;  StateMachine[1] = 6'd17;
StateMachine[2] = 6'd29;  StateMachine[3] =  6'd37;
StateMachine[4] =  6'd12;  StateMachine[5] = 6'd0;
StateMachine[6] = 6'd0;  StateMachine[7] = 6'd0;
StateMachine[8] = 6'd0;  StateMachine[9] = 6'd0; 
StateMachine[10] = 6'd45; StateMachine[11] = 6'd14;
StateMachine[12] = 6'd20; StateMachine[13] = 6'd29;
StateMachine[14] = 6'd0; StateMachine[15] = 6'd0;
end

wire [3:0] address; // 16 linhas , 4 bits de endereco
wire [5:0] dout;  // 6 bits de largura , 3 do próx e 3 da saída

assign address[3] = a;
assign dout = StateMachine[address];
assign s = dout[2:0]; // Saída são os 3 primeiros bits do dout

// ff para repassar o próximo estado para o e2e1e0
ff st0(dout[3],clk,res,address[0]);
ff st1(dout[4],clk,res,address[1]);
ff st2(dout[5],clk,res,address[2]);

endmodule

module main;
reg c,res,a;
wire [2:0] s;
wire [2:0] s1;
wire [2:0] s2;
statem FSM(c,res,a,s);
statePorta FSM1(c,res,a,s1);
stateMem FSM2(c,res,a,s2);

initial
    c = 1'b0;
  always
    c= #(1) ~c;

// visualizar formas de onda usar gtkwave out.vcd
initial  begin
     $dumpfile ("out.vcd"); 
     $dumpvars; 
   end 

  initial 
    begin
     $monitor($time," c %b res %b a %b s %d s1 %d s2 %d",c,res,a,s,s1,s2);
        #1 res=0; a=0;
        #1 res=1;
        #8 a=1;
        #16 a=0;
        #12 a=1;
        #4;
        $finish ;
    end
endmodule

t2/out.vcd
$date
	Fri Sep 28 01:47:14 2018
$end
$version
	Icarus Verilog
$end
$timescale
	1s
$end
$scope module main $end
$var wire 3 ! s2 [2:0] $end
$var wire 3 " s1 [2:0] $end
$var wire 3 # s [2:0] $end
$var reg 1 $ a $end
$var reg 1 % c $end
$var reg 1 & res $end
$scope module FSM $end
$var wire 1 $ a $end
$var wire 1 % clk $end
$var wire 1 & reset $end
$var wire 3 ' s [2:0] $end
$var reg 3 ( state [2:0] $end
$upscope $end
$scope module FSM1 $end
$var wire 1 $ a $end
$var wire 1 % clk $end
$var wire 1 & res $end
$var wire 3 ) s [2:0] $end
$var wire 3 * p [2:0] $end
$var wire 3 + e [2:0] $end
$scope module e0 $end
$var wire 1 % c $end
$var wire 1 , data $end
$var wire 1 & r $end
$var reg 1 - q $end
$upscope $end
$scope module e1 $end
$var wire 1 % c $end
$var wire 1 . data $end
$var wire 1 & r $end
$var reg 1 / q $end
$upscope $end
$scope module e2 $end
$var wire 1 % c $end
$var wire 1 0 data $end
$var wire 1 & r $end
$var reg 1 1 q $end
$upscope $end
$upscope $end
$scope module FSM2 $end
$var wire 1 $ a $end
$var wire 1 % clk $end
$var wire 6 2 dout [5:0] $end
$var wire 1 & res $end
$var wire 3 3 s [2:0] $end
$var wire 4 4 address [3:0] $end
$scope module st0 $end
$var wire 1 % c $end
$var wire 1 5 data $end
$var wire 1 & r $end
$var reg 1 6 q $end
$upscope $end
$scope module st1 $end
$var wire 1 % c $end
$var wire 1 7 data $end
$var wire 1 & r $end
$var reg 1 8 q $end
$upscope $end
$scope module st2 $end
$var wire 1 % c $end
$var wire 1 9 data $end
$var wire 1 & r $end
$var reg 1 : q $end
$upscope $end
$upscope $end
$upscope $end
$enddefinitions $end
#0
$dumpvars
x:
x9
x8
x7
x6
x5
bx 4
bx 3
bx 2
x1
x0
x/
x.
x-
x,
bx +
bx *
bx )
bx (
bx '
x&
0%
x$
bx #
bx "
bx !
$end
#1
1.
0,
00
b10 *
b0 !
b0 3
05
07
09
0-
0/
b0 "
b0 )
b0 +
01
b0 2
06
08
0:
b0 #
b0 '
b0 (
b0 4
0$
0&
1%
#2
1&
0%
#3
1,
b11 *
b10 "
b10 )
b10 +
1/
1%
#4
0%
#5
0.
0,
10
b100 *
b11 "
b11 )
b11 +
1-
1%
#6
0%
#7
1.
00
b10 *
11
0/
b100 "
b100 )
b100 +
0-
1%
#8
0%
#9
1,
1.
b11 *
1/
b10 "
b10 )
b10 +
01
1%
#10
0.
b1 *
0%
b1000 4
1$
#11
0,
b0 *
0/
b1 "
b1 )
b1 +
1-
1%
#12
0%
#13
b0 "
b0 )
b0 +
0-
1%
#14
0%
#15
1%
#16
0%
#17
1%
#18
0%
#19
1%
#20
0%
#21
1%
#22
0%
#23
1%
#24
0%
#25
1%
#26
1.
b10 *
0%
b0 4
0$
#27
1,
b11 *
b10 "
b10 )
b10 +
1/
1%
#28
0%
#29
0.
0,
10
b100 *
b11 "
b11 )
b11 +
1-
1%
#30
0%
#31
1.
00
b10 *
11
0/
b100 "
b100 )
b100 +
0-
1%
#32
0%
#33
1,
1.
b11 *
1/
b10 "
b10 )
b10 +
01
1%
#34
0%
#35
0.
0,
10
b100 *
b11 "
b11 )
b11 +
1-
1%
#36
0%
#37
00
1.
b10 *
0-
0/
b100 "
b100 )
b100 +
11
1%
#38
0.
1,
b1 *
0%
b1000 4
1$
#39
0,
b0 *
01
b1 "
b1 )
b1 +
1-
1%
#40
0%
#41
b0 "
b0 )
b0 +
0-
1%
